{
  "flutterType": "Container",
  "color": "schema:background",
  "padding": "10,10,10,10",
  "child": {
    "flutterType": "Column",
    "mainAxisSize": "min",
    "children": [
      {
        "flutterType": "TextField",
        "onChangedNotify": false,
        "keyboardType": "emailAddress",
        "textCapitalization": "none",
        "style": {
          "flutterType": "TextStyle",
          "fontSize": 17
        },
        "onSubmitted": {
          "jsInvoke": "Account.js",
          "args": {
            "includeStateData": true,
            "switch": "GetCode"
          }
        },
        "name": "EmailValue",
        "decoration": {
          "flutterType": "InputDecoration",
          "hintText": "E-mail",
          "contentPadding": "15,0,15,0",
          "filled": true,
          "fillColor": "schema:onBackground",
          "border": {
            "flutterType": "OutlineInputBorder"
          },
          "suffixIconConstraints": {
            "flutterType": "BoxConstraints",
            "minHeight": 44,
            "maxHeight": 44
          },
          "suffixIcon": {
            "flutterType": "IconButton",
            "padding": 0,
            "icon": {
              "flutterType": "Icon",
              "color": "grey",
              "src": "clear",
              "size": 18
            },
            "onPressed": {
              "sysInvoke": "ResetTextController",
              "args": {
                "key": "EmailValue"
              }
            }
          },
          "enabledBorder": {
            "flutterType": "OutlineInputBorder",
            "borderRadius": 10,
            "borderSide": {
              "flutterType": "BorderSide",
              "color": "transparent",
              "width": 0
            }
          },
          "focusedBorder": {
            "flutterType": "OutlineInputBorder",
            "borderRadius": 10,
            "borderSide": {
              "flutterType": "BorderSide",
              "color": "transparent",
              "width": 0
            }
          }
        }
      },
      {
        "flutterType": "SizedBox",
        "height": 20
      },
      {
        "flutterType": "MaterialButton",
        "height": 44,
        "child": {
          "flutterType": "Text",
          "label": "Получить код",
          "style": {
            "flutterType": "TextStyle",
            "fontSize": 14,
            "color": "white"
          }
        },
        "shape": {
          "flutterType": "RoundedRectangleBorder",
          "borderRadius": 10
        },
        "onPressed": {
          "jsInvoke": "Account.js",
          "args": {
            "includeStateData": true,
            "switch": "GetCode"
          }
        }
      }
    ]
  }
}